README.md
pyproject.toml
setup.py
src/prescaling/__init__.py
src/prescaling/example.py
src/prescaling.egg-info/PKG-INFO
src/prescaling.egg-info/SOURCES.txt
src/prescaling.egg-info/dependency_links.txt
src/prescaling.egg-info/top_level.txt